gelpy/__init__.py
gelpy/background_BackgroundHandler.py
gelpy/background_ransac_fit_models.py
gelpy/image_handling.py
gelpy/line_profile_handling.py
gelpy/package_api.py
gelpy/profile_fit_handling.py
gelpy/profile_fitting_models.py
gelpy/utility_functions.py
gelpy-0.0.4.dist-info/METADATA
gelpy-0.0.4.dist-info/WHEEL
gelpy-0.0.4.dist-info/licenses/LICENSE
gelpy-0.0.4.dist-info/RECORD
