Metadata-Version: 2.3
Name: gelpy
Version: 0.0.4
Summary: This project is deprecated and no longer maintained. A small python package used for gel electrophoresis visualization, fitting and analysis
Project-URL: homepage, https://github.com/ckarfusehr/GelPy
Project-URL: bug-tracker, https://github.com/ckarfusehr/GelPy/issues
Author-email: Christoph Karfusehr <c.karfusehr@gmail.com>
License-File: LICENSE
Classifier: License :: OSI Approved :: GNU General Public License v3 or later (GPLv3+)
Classifier: Operating System :: OS Independent
Classifier: Programming Language :: Python :: 3
Requires-Python: >=3.10
Requires-Dist: ipykernel>=6.19.2
Requires-Dist: matplotlib>=3.7.1
Requires-Dist: numpy>=1.24.3
Requires-Dist: pandas>=2.0.2
Requires-Dist: scikit-image>=0.21.0
Requires-Dist: scikit-learn>=1.2.2
Requires-Dist: scipy>=1.10.1
Requires-Dist: seaborn>=0.12.2
